bcTesting/__init__.py
bcTesting/testBase.py
bcTesting/maya/__init__.py
bcTesting/maya/fixtures.py
bcTesting/maya/taseBase.py
bcTesting-0.3.2.dist-info/DESCRIPTION.rst
bcTesting-0.3.2.dist-info/METADATA
bcTesting-0.3.2.dist-info/RECORD
bcTesting-0.3.2.dist-info/WHEEL
bcTesting-0.3.2.dist-info/metadata.json
bcTesting-0.3.2.dist-info/top_level.txt
