Metadata-Version: 2.0
Name: bcTesting
Version: 0.3.2
Summary: A Simple Testing Framework
Home-page: https://github.com/barishcb/testing
Author: Barish Chandran B
Author-email: barishcb@gmail.com
License: MIT
Keywords: bcTesting unittest setuptools development
Platform: UNKNOWN
Classifier: Development Status :: 5 - Production/Stable
Classifier: Intended Audience :: Developers
Classifier: Topic :: Software Development :: Build Tools
Classifier: License :: OSI Approved :: MIT License
Classifier: Programming Language :: Python :: 2.7
Requires-Dist: mock (>=1.0)
Requires-Dist: mox (>=0.5)
Requires-Dist: testtools (>=1.8)
Provides-Extra: dev
Requires-Dist: check-manifest; extra == 'dev'
Provides-Extra: test
Requires-Dist: coverage; extra == 'test'
